iemap_mi/__init__.py
iemap_mi/__version__.py
iemap_mi/_utils_hash.py
iemap_mi/ai_handler.py
iemap_mi/example.py
iemap_mi/iemap_mi.py
iemap_mi/iemap_stat.py
iemap_mi/models.py
iemap_mi/project_handler.py
iemap_mi/settings.py
iemap_mi/utils.py
iemap_mi-0.2.6.dist-info/METADATA
iemap_mi-0.2.6.dist-info/WHEEL
iemap_mi-0.2.6.dist-info/RECORD
