Metadata-Version: 2.1
Name: iemap-mi
Version: 0.2.6
Summary: A Python module to interact with the IEMAP REST API
Author: Sergio Ferlito
Author-email: sergio.ferlito@enea.it
Requires-Python: >=3.10,<4.0
Classifier: Programming Language :: Python :: 3
Classifier: Programming Language :: Python :: 3.10
Classifier: Programming Language :: Python :: 3.11
Classifier: Programming Language :: Python :: 3.12
Requires-Dist: httpx (>=0.27.0,<0.28.0)
Requires-Dist: pydantic[email] (>=2.8.2,<3.0.0)
Requires-Dist: stdiomask (>=0.0.6,<0.0.7)
